igor2txt.py
setup.py
igor2txt.egg-info/PKG-INFO
igor2txt.egg-info/SOURCES.txt
igor2txt.egg-info/dependency_links.txt
igor2txt.egg-info/requires.txt
igor2txt.egg-info/top_level.txt