Metadata-Version: 1.1
Name: igor2txt
Version: 0.1
Summary: Extract ASCII waves from Igor *.pxp, *.pxt & *.ibw files
Home-page: http://www.python.org/igor2txt/
Author: Liam Deacon
Author-email: liam.deacon@diamond.ac.uk
License: MIT License
Keywords: phaseshifts atomic scattering muffin-tin diffraction
Platform: UNKNOWN
Classifier: Environment :: Console
Classifier: Intended Audience :: Science/Research
Classifier: License :: OSI Approved :: MIT License
Classifier: Operating System :: OS Independent
Classifier: Programming Language :: Python
Classifier: Topic :: Scientific/Engineering :: Chemistry
Classifier: Topic :: Scientific/Engineering :: Physics
